{"download": 16705042.523142433, "upload": 2820324.635673937, "ping": 13.989, "server": {"url": "http://speedtest.net-d-sign.de:8080/speedtest/upload.php", "lat": "48.2489", "lon": "11.6532", "name": "Garching", "country": "Germany", "cc": "DE", "sponsor": "Net-D-Sign GmbH", "id": "8908", "url2": "http://sp2.net-d-sign.de/upload.php", "host": "speedtest.net-d-sign.de:8080", "d": 12.133542045422844, "latency": 13.989}, "timestamp": "2019-09-06T08:32:03.218942Z", "bytes_sent": 3833856, "bytes_received": 21042672, "share": null, "client": {"ip": "95.114.97.128", "lat": "48.1497", "lon": "11.585", "isp": "O2 Deutschland", "isprating": "3.7", "rating": "0", "ispdlavg": "0", "ispulavg": "0", "loggedin": "0", "country": "DE"}}